firstgalaxydata/Example_firstgalaxydata.py
firstgalaxydata/__init__.py
firstgalaxydata/firstgalaxydata.py
firstgalaxydata/galaxy_data.zip
firstgalaxydata/galaxy_data_crossvalid_0_h5.zip
firstgalaxydata/galaxy_data_crossvalid_1_h5.zip
firstgalaxydata/galaxy_data_crossvalid_2_h5.zip
firstgalaxydata/galaxy_data_crossvalid_3_h5.zip
firstgalaxydata/galaxy_data_crossvalid_4_h5.zip
firstgalaxydata/galaxy_data_crossvalid_test_h5.zip
firstgalaxydata/galaxy_data_h5.zip
firstgalaxydata-0.2.1.dist-info/LICENSE
firstgalaxydata-0.2.1.dist-info/METADATA
firstgalaxydata-0.2.1.dist-info/WHEEL
firstgalaxydata-0.2.1.dist-info/top_level.txt
firstgalaxydata-0.2.1.dist-info/RECORD
