Metadata-Version: 2.1
Name: firstgalaxydata
Version: 0.2.1
Author: Florian Griese
Classifier: Programming Language :: Python :: 3
Classifier: License :: OSI Approved :: MIT License
Classifier: Operating System :: OS Independent
Requires-Python: >=3.6
License-File: LICENSE
Requires-Dist: numpy
Requires-Dist: pillow
Requires-Dist: torch
Requires-Dist: torchvision
Requires-Dist: astropy
Requires-Dist: matplotlib
Requires-Dist: h5py
